[{"achievements":[{"date":{"date":1,"hours":0,"seconds":0,"nanos":0,"month":0,"timezoneOffset":360,"year":117,"minutes":0,"time":1483250400000,"day":0},"achievementType":"PROGRESS","data":90.0},{"date":{"date":1,"hours":0,"seconds":0,"nanos":0,"month":0,"timezoneOffset":360,"year":118,"minutes":0,"time":1514786400000,"day":1},"achievementType":"PROGRESS","data":77.0},{"date":{"date":1,"hours":0,"seconds":0,"nanos":0,"month":0,"timezoneOffset":360,"year":117,"minutes":0,"time":1483250400000,"day":0},"achievementType":"GOAL","data":95.0},{"date":{"date":1,"hours":0,"seconds":0,"nanos":0,"month":0,"timezoneOffset":360,"year":118,"minutes":0,"time":1514786400000,"day":1},"achievementType":"GOAL","data":80.0}],"resetType":{"name":"Continuo","id":1},"description":"","measureUnit":{"type":{"name":"number","id":1}},"grades":[{"maxPercentage":35,"color":"red"},{"maxPercentage":60,"color":"orange"},{"maxPercentage":80,"color":"yellow"},{"maxPercentage":100,"color":"green"}],"perdiodicity":{"name":"Mensual","id":1},"indicatorType":1,"strategicItem":42,"responsible":{"area":{"name":"RECTORIA","id":1},"jobTitle":{"name":"RECTOR","id":1},"id":1,"player":{"name":"Victor González Álvarez","phones":[{"number":"ND","type":"OFFICE"},{"number":"ND","type":"OFFICE"},{"number":"ND","type":"OFFICE"}]}},"resetDates":[],"name":"1.1.1 Peso en Kg","id":1,"direction":"POSITIVE"},{"achievements":[{"date":{"date":1,"hours":0,"seconds":0,"nanos":0,"month":0,"timezoneOffset":360,"year":117,"minutes":0,"time":1483250400000,"day":0},"achievementType":"PROGRESS","data":18.0},{"date":{"date":1,"hours":0,"seconds":0,"nanos":0,"month":0,"timezoneOffset":360,"year":118,"minutes":0,"time":1514786400000,"day":1},"achievementType":"PROGRESS","data":40.0},{"date":{"date":1,"hours":0,"seconds":0,"nanos":0,"month":0,"timezoneOffset":360,"year":117,"minutes":0,"time":1483250400000,"day":0},"achievementType":"GOAL","data":20.0},{"date":{"date":1,"hours":0,"seconds":0,"nanos":0,"month":0,"timezoneOffset":360,"year":118,"minutes":0,"time":1514786400000,"day":1},"achievementType":"GOAL","data":40.0}],"resetType":{"name":"Continuo","id":1},"description":"","measureUnit":{"type":{"name":"number","id":1}},"grades":[{"maxPercentage":35,"color":"red"},{"maxPercentage":60,"color":"orange"},{"maxPercentage":80,"color":"yellow"},{"maxPercentage":100,"color":"green"}],"perdiodicity":{"name":"Mensual","id":1},"indicatorType":1,"strategicItem":43,"responsible":{"area":{"name":"RECTORIA","id":1},"jobTitle":{"name":"RECTOR","id":1},"id":1,"player":{"name":"Victor González Álvarez","phones":[{"number":"ND","type":"OFFICE"},{"number":"ND","type":"OFFICE"},{"number":"ND","type":"OFFICE"}]}},"resetDates":[],"name":"1.2.1 Horas invertidas en actividades que me mejoren como persona","id":2,"direction":"POSITIVE"},{"achievements":[{"date":{"date":1,"hours":0,"seconds":0,"nanos":0,"month":0,"timezoneOffset":360,"year":117,"minutes":0,"time":1483250400000,"day":0},"achievementType":"PROGRESS","data":10.0},{"date":{"date":1,"hours":0,"seconds":0,"nanos":0,"month":0,"timezoneOffset":360,"year":118,"minutes":0,"time":1514786400000,"day":1},"achievementType":"PROGRESS","data":22.0},{"date":{"date":1,"hours":0,"seconds":0,"nanos":0,"month":0,"timezoneOffset":360,"year":117,"minutes":0,"time":1483250400000,"day":0},"achievementType":"GOAL","data":10.0},{"date":{"date":1,"hours":0,"seconds":0,"nanos":0,"month":0,"timezoneOffset":360,"year":118,"minutes":0,"time":1514786400000,"day":1},"achievementType":"GOAL","data":20.0}],"resetType":{"name":"Continuo","id":1},"description":"","measureUnit":{"type":{"name":"number","id":1}},"grades":[{"maxPercentage":35,"color":"red"},{"maxPercentage":60,"color":"orange"},{"maxPercentage":80,"color":"yellow"},{"maxPercentage":100,"color":"green"}],"perdiodicity":{"name":"Mensual","id":1},"indicatorType":1,"strategicItem":45,"responsible":{"area":{"name":"RECTORIA","id":1},"jobTitle":{"name":"RECTOR","id":1},"id":1,"player":{"name":"Victor González Álvarez","phones":[{"number":"ND","type":"OFFICE"},{"number":"ND","type":"OFFICE"},{"number":"ND","type":"OFFICE"}]}},"resetDates":[],"name":"1.3.1 Número de atuendos mejorados","id":3,"direction":"POSITIVE"},{"achievements":[{"date":{"date":1,"hours":0,"seconds":0,"nanos":0,"month":0,"timezoneOffset":360,"year":117,"minutes":0,"time":1483250400000,"day":0},"achievementType":"PROGRESS","data":55.0},{"date":{"date":1,"hours":0,"seconds":0,"nanos":0,"month":0,"timezoneOffset":360,"year":118,"minutes":0,"time":1514786400000,"day":1},"achievementType":"PROGRESS","data":110.0},{"date":{"date":1,"hours":0,"seconds":0,"nanos":0,"month":0,"timezoneOffset":360,"year":117,"minutes":0,"time":1483250400000,"day":0},"achievementType":"GOAL","data":50.0},{"date":{"date":1,"hours":0,"seconds":0,"nanos":0,"month":0,"timezoneOffset":360,"year":118,"minutes":0,"time":1514786400000,"day":1},"achievementType":"GOAL","data":100.0}],"resetType":{"name":"Continuo","id":1},"description":"","measureUnit":{"type":{"name":"number","id":1}},"grades":[{"maxPercentage":35,"color":"red"},{"maxPercentage":60,"color":"orange"},{"maxPercentage":80,"color":"yellow"},{"maxPercentage":100,"color":"green"}],"perdiodicity":{"name":"Mensual","id":1},"indicatorType":1,"strategicItem":44,"responsible":{"area":{"name":"RECTORIA","id":1},"jobTitle":{"name":"RECTOR","id":1},"id":1,"player":{"name":"Victor González Álvarez","phones":[{"number":"ND","type":"OFFICE"},{"number":"ND","type":"OFFICE"},{"number":"ND","type":"OFFICE"}]}},"resetDates":[],"name":"1.4.1 Situaciones negativas en las que reaccioné de manera positiva","id":4,"direction":"POSITIVE"},{"achievements":[{"date":{"date":1,"hours":0,"seconds":0,"nanos":0,"month":0,"timezoneOffset":360,"year":117,"minutes":0,"time":1483250400000,"day":0},"achievementType":"PROGRESS","data":80.0},{"date":{"date":1,"hours":0,"seconds":0,"nanos":0,"month":0,"timezoneOffset":360,"year":118,"minutes":0,"time":1514786400000,"day":1},"achievementType":"PROGRESS","data":150.0},{"date":{"date":1,"hours":0,"seconds":0,"nanos":0,"month":0,"timezoneOffset":360,"year":117,"minutes":0,"time":1483250400000,"day":0},"achievementType":"GOAL","data":100.0},{"date":{"date":1,"hours":0,"seconds":0,"nanos":0,"month":0,"timezoneOffset":360,"year":118,"minutes":0,"time":1514786400000,"day":1},"achievementType":"GOAL","data":200.0}],"resetType":{"name":"Continuo","id":1},"description":"","measureUnit":{"type":{"name":"number","id":1}},"grades":[{"maxPercentage":35,"color":"red"},{"maxPercentage":60,"color":"orange"},{"maxPercentage":80,"color":"yellow"},{"maxPercentage":100,"color":"green"}],"perdiodicity":{"name":"Mensual","id":1},"indicatorType":1,"strategicItem":41,"responsible":{"area":{"name":"RECTORIA","id":1},"jobTitle":{"name":"RECTOR","id":1},"id":1,"player":{"name":"Victor González Álvarez","phones":[{"number":"ND","type":"OFFICE"},{"number":"ND","type":"OFFICE"},{"number":"ND","type":"OFFICE"}]}},"resetDates":[],"name":"1.5.1 Acciones orientadas a buscar y conservar a quienes amo","id":5,"direction":"POSITIVE"},{"achievements":[{"date":{"date":1,"hours":0,"seconds":0,"nanos":0,"month":0,"timezoneOffset":360,"year":117,"minutes":0,"time":1483250400000,"day":0},"achievementType":"PROGRESS","data":60.0},{"date":{"date":1,"hours":0,"seconds":0,"nanos":0,"month":0,"timezoneOffset":360,"year":118,"minutes":0,"time":1514786400000,"day":1},"achievementType":"PROGRESS","data":80.0},{"date":{"date":1,"hours":0,"seconds":0,"nanos":0,"month":0,"timezoneOffset":360,"year":117,"minutes":0,"time":1483250400000,"day":0},"achievementType":"GOAL","data":70.0},{"date":{"date":1,"hours":0,"seconds":0,"nanos":0,"month":0,"timezoneOffset":360,"year":118,"minutes":0,"time":1514786400000,"day":1},"achievementType":"GOAL","data":90.0}],"resetType":{"name":"Continuo","id":1},"description":"","measureUnit":{"type":{"name":"number","id":1}},"grades":[{"maxPercentage":35,"color":"red"},{"maxPercentage":60,"color":"orange"},{"maxPercentage":80,"color":"yellow"},{"maxPercentage":100,"color":"green"}],"perdiodicity":{"name":"Mensual","id":1},"indicatorType":1,"strategicItem":46,"responsible":{"area":{"name":"RECTORIA","id":1},"jobTitle":{"name":"RECTOR","id":1},"id":1,"player":{"name":"Victor González Álvarez","phones":[{"number":"ND","type":"OFFICE"},{"number":"ND","type":"OFFICE"},{"number":"ND","type":"OFFICE"}]}},"resetDates":[],"name":"2.1.1 Porcentaje de platillos considerados nutritivos en la alimentación semanal","id":6,"direction":"POSITIVE"},{"achievements":[{"date":{"date":1,"hours":0,"seconds":0,"nanos":0,"month":0,"timezoneOffset":360,"year":117,"minutes":0,"time":1483250400000,"day":0},"achievementType":"PROGRESS","data":12.0},{"date":{"date":1,"hours":0,"seconds":0,"nanos":0,"month":0,"timezoneOffset":360,"year":118,"minutes":0,"time":1514786400000,"day":1},"achievementType":"PROGRESS","data":21.0},{"date":{"date":1,"hours":0,"seconds":0,"nanos":0,"month":0,"timezoneOffset":360,"year":117,"minutes":0,"time":1483250400000,"day":0},"achievementType":"GOAL","data":10.0},{"date":{"date":1,"hours":0,"seconds":0,"nanos":0,"month":0,"timezoneOffset":360,"year":118,"minutes":0,"time":1514786400000,"day":1},"achievementType":"GOAL","data":20.0}],"resetType":{"name":"Continuo","id":1},"description":"","measureUnit":{"type":{"name":"number","id":1}},"grades":[{"maxPercentage":35,"color":"red"},{"maxPercentage":60,"color":"orange"},{"maxPercentage":80,"color":"yellow"},{"maxPercentage":100,"color":"green"}],"perdiodicity":{"name":"Mensual","id":1},"indicatorType":1,"strategicItem":47,"responsible":{"area":{"name":"RECTORIA","id":1},"jobTitle":{"name":"RECTOR","id":1},"id":1,"player":{"name":"Victor González Álvarez","phones":[{"number":"ND","type":"OFFICE"},{"number":"ND","type":"OFFICE"},{"number":"ND","type":"OFFICE"}]}},"resetDates":[],"name":"2.2.1 Horas de convivencia familiar (semanales)","id":7,"direction":"POSITIVE"},{"achievements":[{"date":{"date":1,"hours":0,"seconds":0,"nanos":0,"month":0,"timezoneOffset":360,"year":117,"minutes":0,"time":1483250400000,"day":0},"achievementType":"PROGRESS","data":12.0},{"date":{"date":1,"hours":0,"seconds":0,"nanos":0,"month":0,"timezoneOffset":360,"year":118,"minutes":0,"time":1514786400000,"day":1},"achievementType":"PROGRESS","data":19.0},{"date":{"date":1,"hours":0,"seconds":0,"nanos":0,"month":0,"timezoneOffset":360,"year":117,"minutes":0,"time":1483250400000,"day":0},"achievementType":"GOAL","data":15.0},{"date":{"date":1,"hours":0,"seconds":0,"nanos":0,"month":0,"timezoneOffset":360,"year":118,"minutes":0,"time":1514786400000,"day":1},"achievementType":"GOAL","data":20.0}],"resetType":{"name":"Continuo","id":1},"description":"","measureUnit":{"type":{"name":"percentage","id":2}},"grades":[{"maxPercentage":35,"color":"red"},{"maxPercentage":60,"color":"orange"},{"maxPercentage":80,"color":"yellow"},{"maxPercentage":100,"color":"green"}],"perdiodicity":{"name":"Mensual","id":1},"indicatorType":1,"strategicItem":48,"responsible":{"area":{"name":"RECTORIA","id":1},"jobTitle":{"name":"RECTOR","id":1},"id":1,"player":{"name":"Victor González Álvarez","phones":[{"number":"ND","type":"OFFICE"},{"number":"ND","type":"OFFICE"},{"number":"ND","type":"OFFICE"}]}},"resetDates":[],"name":"2.3.1 Proyectos de mejora del hogar terminados","id":8,"direction":"POSITIVE"},{"achievements":[{"date":{"date":1,"hours":0,"seconds":0,"nanos":0,"month":0,"timezoneOffset":360,"year":117,"minutes":0,"time":1483250400000,"day":0},"achievementType":"PROGRESS","data":50.0},{"date":{"date":1,"hours":0,"seconds":0,"nanos":0,"month":0,"timezoneOffset":360,"year":118,"minutes":0,"time":1514786400000,"day":1},"achievementType":"PROGRESS","data":70.0},{"date":{"date":1,"hours":0,"seconds":0,"nanos":0,"month":0,"timezoneOffset":360,"year":117,"minutes":0,"time":1483250400000,"day":0},"achievementType":"GOAL","data":70.0},{"date":{"date":1,"hours":0,"seconds":0,"nanos":0,"month":0,"timezoneOffset":360,"year":118,"minutes":0,"time":1514786400000,"day":1},"achievementType":"GOAL","data":85.0}],"resetType":{"name":"Continuo","id":1},"description":"","measureUnit":{"type":{"name":"percentage","id":2}},"grades":[{"maxPercentage":35,"color":"red"},{"maxPercentage":60,"color":"orange"},{"maxPercentage":80,"color":"yellow"},{"maxPercentage":100,"color":"green"}],"perdiodicity":{"name":"Mensual","id":1},"indicatorType":1,"strategicItem":49,"responsible":{"area":{"name":"RECTORIA","id":1},"jobTitle":{"name":"RECTOR","id":1},"id":1,"player":{"name":"Victor González Álvarez","phones":[{"number":"ND","type":"OFFICE"},{"number":"ND","type":"OFFICE"},{"number":"ND","type":"OFFICE"}]}},"resetDates":[],"name":"2.4.1 Porcentaje de tareas del hogar que se cumplen como rol personal","id":9,"direction":"POSITIVE"},{"achievements":[{"date":{"date":1,"hours":0,"seconds":0,"nanos":0,"month":0,"timezoneOffset":360,"year":117,"minutes":0,"time":1483250400000,"day":0},"achievementType":"PROGRESS","data":130.0},{"date":{"date":1,"hours":0,"seconds":0,"nanos":0,"month":0,"timezoneOffset":360,"year":118,"minutes":0,"time":1514786400000,"day":1},"achievementType":"PROGRESS","data":120.0},{"date":{"date":1,"hours":0,"seconds":0,"nanos":0,"month":0,"timezoneOffset":360,"year":117,"minutes":0,"time":1483250400000,"day":0},"achievementType":"GOAL","data":120.0},{"date":{"date":1,"hours":0,"seconds":0,"nanos":0,"month":0,"timezoneOffset":360,"year":118,"minutes":0,"time":1514786400000,"day":1},"achievementType":"GOAL","data":150.0}],"resetType":{"name":"Continuo","id":1},"description":"","measureUnit":{"type":{"name":"number","id":1}},"grades":[{"maxPercentage":35,"color":"red"},{"maxPercentage":60,"color":"orange"},{"maxPercentage":80,"color":"yellow"},{"maxPercentage":100,"color":"green"}],"perdiodicity":{"name":"Mensual","id":1},"indicatorType":1,"strategicItem":51,"responsible":{"area":{"name":"RECTORIA","id":1},"jobTitle":{"name":"RECTOR","id":1},"id":1,"player":{"name":"Victor González Álvarez","phones":[{"number":"ND","type":"OFFICE"},{"number":"ND","type":"OFFICE"},{"number":"ND","type":"OFFICE"}]}},"resetDates":[],"name":"3.1.1 Actividades religiosas a las que he asistido","id":10,"direction":"POSITIVE"},{"achievements":[{"date":{"date":1,"hours":0,"seconds":0,"nanos":0,"month":0,"timezoneOffset":360,"year":117,"minutes":0,"time":1483250400000,"day":0},"achievementType":"PROGRESS","data":30.0},{"date":{"date":1,"hours":0,"seconds":0,"nanos":0,"month":0,"timezoneOffset":360,"year":118,"minutes":0,"time":1514786400000,"day":1},"achievementType":"PROGRESS","data":44.0},{"date":{"date":1,"hours":0,"seconds":0,"nanos":0,"month":0,"timezoneOffset":360,"year":117,"minutes":0,"time":1483250400000,"day":0},"achievementType":"GOAL","data":30.0},{"date":{"date":1,"hours":0,"seconds":0,"nanos":0,"month":0,"timezoneOffset":360,"year":118,"minutes":0,"time":1514786400000,"day":1},"achievementType":"GOAL","data":50.0}],"resetType":{"name":"Continuo","id":1},"description":"","measureUnit":{"type":{"name":"number","id":1}},"grades":[{"maxPercentage":35,"color":"red"},{"maxPercentage":60,"color":"orange"},{"maxPercentage":80,"color":"yellow"},{"maxPercentage":100,"color":"green"}],"perdiodicity":{"name":"Mensual","id":1},"indicatorType":1,"strategicItem":53,"responsible":{"area":{"name":"RECTORIA","id":1},"jobTitle":{"name":"RECTOR","id":1},"id":1,"player":{"name":"Victor González Álvarez","phones":[{"number":"ND","type":"OFFICE"},{"number":"ND","type":"OFFICE"},{"number":"ND","type":"OFFICE"}]}},"resetDates":[],"name":"3.2.1 Actividades realizadas en convivencia con los vecinos","id":11,"direction":"POSITIVE"},{"achievements":[{"date":{"date":1,"hours":0,"seconds":0,"nanos":0,"month":0,"timezoneOffset":360,"year":117,"minutes":0,"time":1483250400000,"day":0},"achievementType":"PROGRESS","data":5.0},{"date":{"date":1,"hours":0,"seconds":0,"nanos":0,"month":0,"timezoneOffset":360,"year":118,"minutes":0,"time":1514786400000,"day":1},"achievementType":"PROGRESS","data":8.0},{"date":{"date":1,"hours":0,"seconds":0,"nanos":0,"month":0,"timezoneOffset":360,"year":117,"minutes":0,"time":1483250400000,"day":0},"achievementType":"GOAL","data":12.0},{"date":{"date":1,"hours":0,"seconds":0,"nanos":0,"month":0,"timezoneOffset":360,"year":118,"minutes":0,"time":1514786400000,"day":1},"achievementType":"GOAL","data":18.0}],"resetType":{"name":"Continuo","id":1},"description":"","measureUnit":{"type":{"name":"number","id":1}},"grades":[{"maxPercentage":35,"color":"red"},{"maxPercentage":60,"color":"orange"},{"maxPercentage":80,"color":"yellow"},{"maxPercentage":100,"color":"green"}],"perdiodicity":{"name":"Mensual","id":1},"indicatorType":1,"strategicItem":52,"responsible":{"area":{"name":"RECTORIA","id":1},"jobTitle":{"name":"RECTOR","id":1},"id":1,"player":{"name":"Victor González Álvarez","phones":[{"number":"ND","type":"OFFICE"},{"number":"ND","type":"OFFICE"},{"number":"ND","type":"OFFICE"}]}},"resetDates":[],"name":"3.3.1 Actividades varias en apoyo a las festividades comunitarias","id":12,"direction":"POSITIVE"},{"achievements":[{"date":{"date":1,"hours":0,"seconds":0,"nanos":0,"month":0,"timezoneOffset":360,"year":117,"minutes":0,"time":1483250400000,"day":0},"achievementType":"PROGRESS","data":7.0},{"date":{"date":1,"hours":0,"seconds":0,"nanos":0,"month":0,"timezoneOffset":360,"year":118,"minutes":0,"time":1514786400000,"day":1},"achievementType":"PROGRESS","data":18.0},{"date":{"date":1,"hours":0,"seconds":0,"nanos":0,"month":0,"timezoneOffset":360,"year":117,"minutes":0,"time":1483250400000,"day":0},"achievementType":"GOAL","data":7.0},{"date":{"date":1,"hours":0,"seconds":0,"nanos":0,"month":0,"timezoneOffset":360,"year":118,"minutes":0,"time":1514786400000,"day":1},"achievementType":"GOAL","data":15.0}],"resetType":{"name":"Continuo","id":1},"description":"","measureUnit":{"type":{"name":"number","id":1}},"grades":[{"maxPercentage":35,"color":"red"},{"maxPercentage":60,"color":"orange"},{"maxPercentage":80,"color":"yellow"},{"maxPercentage":100,"color":"green"}],"perdiodicity":{"name":"Mensual","id":1},"indicatorType":1,"strategicItem":50,"responsible":{"area":{"name":"RECTORIA","id":1},"jobTitle":{"name":"RECTOR","id":1},"id":1,"player":{"name":"Victor González Álvarez","phones":[{"number":"ND","type":"OFFICE"},{"number":"ND","type":"OFFICE"},{"number":"ND","type":"OFFICE"}]}},"resetDates":[],"name":"3.4.1 Acciones realizadas en beneficio de personas desfavorecidas","id":13,"direction":"POSITIVE"},{"achievements":[{"date":{"date":1,"hours":0,"seconds":0,"nanos":0,"month":0,"timezoneOffset":360,"year":117,"minutes":0,"time":1483250400000,"day":0},"achievementType":"PROGRESS","data":50.0},{"date":{"date":1,"hours":0,"seconds":0,"nanos":0,"month":0,"timezoneOffset":360,"year":118,"minutes":0,"time":1514786400000,"day":1},"achievementType":"PROGRESS","data":50.0},{"date":{"date":1,"hours":0,"seconds":0,"nanos":0,"month":0,"timezoneOffset":360,"year":117,"minutes":0,"time":1483250400000,"day":0},"achievementType":"GOAL","data":80.0},{"date":{"date":1,"hours":0,"seconds":0,"nanos":0,"month":0,"timezoneOffset":360,"year":118,"minutes":0,"time":1514786400000,"day":1},"achievementType":"GOAL","data":90.0}],"resetType":{"name":"Continuo","id":1},"description":"","measureUnit":{"type":{"name":"percentage","id":2}},"grades":[{"maxPercentage":35,"color":"red"},{"maxPercentage":60,"color":"orange"},{"maxPercentage":80,"color":"yellow"},{"maxPercentage":100,"color":"green"}],"perdiodicity":{"name":"Mensual","id":1},"indicatorType":1,"strategicItem":54,"responsible":{"area":{"name":"RECTORIA","id":1},"jobTitle":{"name":"RECTOR","id":1},"id":1,"player":{"name":"Victor González Álvarez","phones":[{"number":"ND","type":"OFFICE"},{"number":"ND","type":"OFFICE"},{"number":"ND","type":"OFFICE"}]}},"resetDates":[],"name":"4.1.1 Porcentaje de felicidad que me otorga mi trabajo","id":14,"direction":"POSITIVE"},{"achievements":[{"date":{"date":1,"hours":0,"seconds":0,"nanos":0,"month":0,"timezoneOffset":360,"year":117,"minutes":0,"time":1483250400000,"day":0},"achievementType":"PROGRESS","data":1.0},{"date":{"date":1,"hours":0,"seconds":0,"nanos":0,"month":0,"timezoneOffset":360,"year":118,"minutes":0,"time":1514786400000,"day":1},"achievementType":"PROGRESS","data":3.0},{"date":{"date":1,"hours":0,"seconds":0,"nanos":0,"month":0,"timezoneOffset":360,"year":117,"minutes":0,"time":1483250400000,"day":0},"achievementType":"GOAL","data":3.0},{"date":{"date":1,"hours":0,"seconds":0,"nanos":0,"month":0,"timezoneOffset":360,"year":118,"minutes":0,"time":1514786400000,"day":1},"achievementType":"GOAL","data":8.0}],"resetType":{"name":"Continuo","id":1},"description":"","measureUnit":{"type":{"name":"number","id":1}},"grades":[{"maxPercentage":35,"color":"red"},{"maxPercentage":60,"color":"orange"},{"maxPercentage":80,"color":"yellow"},{"maxPercentage":100,"color":"green"}],"perdiodicity":{"name":"Mensual","id":1},"indicatorType":1,"strategicItem":56,"responsible":{"area":{"name":"RECTORIA","id":1},"jobTitle":{"name":"RECTOR","id":1},"id":1,"player":{"name":"Victor González Álvarez","phones":[{"number":"ND","type":"OFFICE"},{"number":"ND","type":"OFFICE"},{"number":"ND","type":"OFFICE"}]}},"resetDates":[],"name":"4.2.1 Habilidades nuevas adquiridas en favor de mi profesión","id":15,"direction":"POSITIVE"},{"achievements":[{"date":{"date":1,"hours":0,"seconds":0,"nanos":0,"month":0,"timezoneOffset":360,"year":117,"minutes":0,"time":1483250400000,"day":0},"achievementType":"PROGRESS","data":18000.0},{"date":{"date":1,"hours":0,"seconds":0,"nanos":0,"month":0,"timezoneOffset":360,"year":118,"minutes":0,"time":1514786400000,"day":1},"achievementType":"PROGRESS","data":18000.0},{"date":{"date":1,"hours":0,"seconds":0,"nanos":0,"month":0,"timezoneOffset":360,"year":117,"minutes":0,"time":1483250400000,"day":0},"achievementType":"GOAL","data":20000.0},{"date":{"date":1,"hours":0,"seconds":0,"nanos":0,"month":0,"timezoneOffset":360,"year":118,"minutes":0,"time":1514786400000,"day":1},"achievementType":"GOAL","data":30000.0}],"resetType":{"name":"Continuo","id":1},"description":"","measureUnit":{"type":{"name":"number","id":1}},"grades":[{"maxPercentage":35,"color":"red"},{"maxPercentage":60,"color":"orange"},{"maxPercentage":80,"color":"yellow"},{"maxPercentage":100,"color":"green"}],"perdiodicity":{"name":"Mensual","id":1},"indicatorType":1,"strategicItem":57,"responsible":{"area":{"name":"RECTORIA","id":1},"jobTitle":{"name":"RECTOR","id":1},"id":1,"player":{"name":"Victor González Álvarez","phones":[{"number":"ND","type":"OFFICE"},{"number":"ND","type":"OFFICE"},{"number":"ND","type":"OFFICE"}]}},"resetDates":[],"name":"4.3.1 Sueldo mensual","id":16,"direction":"POSITIVE"},{"achievements":[{"date":{"date":1,"hours":0,"seconds":0,"nanos":0,"month":0,"timezoneOffset":360,"year":117,"minutes":0,"time":1483250400000,"day":0},"achievementType":"PROGRESS","data":3.0},{"date":{"date":1,"hours":0,"seconds":0,"nanos":0,"month":0,"timezoneOffset":360,"year":118,"minutes":0,"time":1514786400000,"day":1},"achievementType":"PROGRESS","data":5.0},{"date":{"date":1,"hours":0,"seconds":0,"nanos":0,"month":0,"timezoneOffset":360,"year":117,"minutes":0,"time":1483250400000,"day":0},"achievementType":"GOAL","data":2.0},{"date":{"date":1,"hours":0,"seconds":0,"nanos":0,"month":0,"timezoneOffset":360,"year":118,"minutes":0,"time":1514786400000,"day":1},"achievementType":"GOAL","data":5.0}],"resetType":{"name":"Continuo","id":1},"description":"","measureUnit":{"type":{"name":"number","id":1}},"grades":[{"maxPercentage":35,"color":"red"},{"maxPercentage":60,"color":"orange"},{"maxPercentage":80,"color":"yellow"},{"maxPercentage":100,"color":"green"}],"perdiodicity":{"name":"Mensual","id":1},"indicatorType":1,"strategicItem":55,"responsible":{"area":{"name":"RECTORIA","id":1},"jobTitle":{"name":"RECTOR","id":1},"id":1,"player":{"name":"Victor González Álvarez","phones":[{"number":"ND","type":"OFFICE"},{"number":"ND","type":"OFFICE"},{"number":"ND","type":"OFFICE"}]}},"resetDates":[],"name":"4.4.1 Nuevas amistades en el círculo profesional","id":17,"direction":"POSITIVE"}]